{"bones":[{"name":"root"},{"name":"bone","parent":"root","x":8.6,"y":204.6},{"name":"bone17","parent":"bone","length":191.73,"x":23.89,"y":-17.6,"rotation":-92.7},{"name":"bone2","parent":"bone","length":185.81,"x":-30.37,"y":-17.57,"rotation":-90},{"name":"bone3","parent":"bone","length":42.71,"y":28.45,"rotation":91.8},{"name":"bone21","parent":"bone3","length":45.73,"x":45.87,"y":-0.82,"rotation":0.9},{"name":"bone6","parent":"bone3","length":77.7,"x":84.69,"y":35.38,"rotation":160.48},{"name":"bone9","parent":"bone3","length":81.3,"x":87.69,"y":-16.03,"rotation":-158.12},{"name":"bone10","parent":"bone9","length":47.05,"x":81.31,"y":0.19,"rotation":128.21},{"name":"bone18","parent":"bone21","length":49.25,"x":40.78,"y":19.13,"rotation":166.22},{"name":"bone19","parent":"bone21","length":48.72,"x":31.9,"y":-25.44,"rotation":-171},{"name":"bone4","parent":"bone21","x":8.2,"y":-15.78,"rotation":-0.9},{"name":"bone5","parent":"bone21","length":133.1,"x":49.77,"y":-6.04,"rotation":-1.36},{"name":"bone7","parent":"bone6","length":67.44,"x":77.7,"y":-0.51,"rotation":-4.05},{"name":"bone11","parent":"bone10","length":29.04,"x":47.04,"y":0.1,"rotation":63.97},{"name":"bone12","parent":"bone5","x":68.38,"y":-9.29},{"name":"bone13","parent":"bone5","x":15.04,"y":-1.84},{"name":"bone14","parent":"bone5","length":100.99,"x":114.86,"y":18.8,"rotation":155.65},{"name":"bone15","parent":"bone5","length":67.96,"x":120.76,"y":-35.67,"rotation":-166.28},{"name":"bone20","parent":"bone5","x":51.47,"y":148.81},{"name":"bone8","parent":"bone7","length":28.06,"x":57.63,"y":-1.84,"rotation":-8.94},{"name":"bone16","parent":"bone15","length":93.5,"x":16.84,"y":-2.7,"rotation":-16.24}],"slots":[{"name":"bone54","bone":"bone5","attachment":"NIco_big_0031_maozihou"},{"name":"NIco_big_0030_toufa","bone":"bone5","attachment":"NIco_big_0030_toufa"},{"name":"NIco_big_0006_zuodabi","bone":"bone9","attachment":"NIco_big_0006_zuodabi"},{"name":"NIco_big_0005_zuoqianbi","bone":"bone10","attachment":"NIco_big_0005_zuoqianbi"},{"name":"NIco_big_0001_zuoshou02","bone":"bone11","attachment":"NIco_big_0001_zuoshou02"},{"name":"NIco_big_0029_waiyizuo","bone":"bone19","attachment":"NIco_big_0029_waiyizuo"},{"name":"rikobig_fin","bone":"root"},{"name":"NIco_big_0028_shentixia","bone":"bone3","attachment":"NIco_big_0028_shentixia"},{"name":"NIco_big_0026_zuotui","bone":"bone17","attachment":"NIco_big_0026_zuotui"},{"name":"NIco_big_0025_kua","bone":"bone","attachment":"NIco_big_0025_kua"},{"name":"NIco_big_0024_youtui","bone":"bone2","attachment":"NIco_big_0024_youtui"},{"name":"NIco_big_0027_xiong","bone":"bone21","attachment":"NIco_big_0027_xiong"},{"name":"BO","bone":"bone4","attachment":"BO"},{"name":"NIco_big_0023_waiyiyou","bone":"bone18","attachment":"NIco_big_0023_waiyiyou"},{"name":"NIco_big_0004_youdabi","bone":"bone6","attachment":"NIco_big_0004_youdabi"},{"name":"bone4","bone":"bone21","attachment":"NIco_big_0022_sijinhou"},{"name":"bone42","bone":"bone21","attachment":"NIco_big_0021_sijin"},{"name":"NIco_big_0003_youqianbi","bone":"bone7","attachment":"NIco_big_0003_youqianbi"},{"name":"NIco_big_0002_youshou","bone":"bone8","attachment":"NIco_big_0002_youshou"},{"name":"bone5","bone":"bone5","attachment":"NIco_big_0020_yanbai"},{"name":"NIco_big_0019_yanqiu","bone":"bone20","attachment":"NIco_big_0019_yanqiu"},{"name":"NIco_big_0019_yanqiu2","bone":"bone20","attachment":"NIco_big_0019_yanqiu"},{"name":"NIco_big_0010_binjiao2","bone":"bone16","attachment":"NIco_big_0010_binjiao2"},{"name":"bone52","bone":"bone5","attachment":"NIco_big_0018_lian"},{"name":"NIco_big_0008_liuhai01","bone":"bone15","attachment":"NIco_big_0008_liuhai01"},{"name":"NIco_big_0009_binjiao","bone":"bone14","attachment":"NIco_big_0009_binjiao"},{"name":"bone53","bone":"bone5","attachment":"NIco_big_0017_yan"},{"name":"NIco_big_0015_kouxing01","bone":"bone13","attachment":"NIco_big_0013_kouxing03"},{"name":"NIco_big_0011_meimao","bone":"bone12","attachment":"NIco_big_0011_meimao"},{"name":"NIco_big_0011_meimao2","bone":"bone12","attachment":"NIco_big_0011_meimao"},{"name":"bone55","bone":"bone5","attachment":"NIco_big_0007_maoziqian"}],"skins":{"default":{"BO":{"BO":{"x":0.26,"y":8.45,"rotation":-91.8,"width":71,"height":43}},"NIco_big_0001_zuoshou02":{"NIco_big_0001_zuoshou02":{"x":17.41,"y":-0.08,"scaleX":-1,"rotation":98.57,"width":24,"height":42}},"NIco_big_0002_youshou":{"NIco_big_0002_youshou":{"x":11.91,"y":-2.41,"rotation":75.56,"width":28,"height":51}},"NIco_big_0003_youqianbi":{"NIco_big_0003_youqianbi":{"x":28.89,"y":-0.81,"rotation":86.5,"width":20,"height":62}},"NIco_big_0004_youdabi":{"NIco_big_0004_youdabi":{"x":40.57,"y":1.16,"rotation":87.2,"width":30,"height":96}},"NIco_big_0005_zuoqianbi":{"NIco_big_0005_zuoqianbi":{"x":26.78,"y":-0.64,"rotation":87.27,"width":18,"height":57}},"NIco_big_0006_zuodabi":{"NIco_big_0006_zuodabi":{"x":38.32,"y":-3.51,"rotation":96.79,"width":29,"height":95}},"NIco_big_0008_liuhai01":{"NIco_big_0008_liuhai01":{"x":37.16,"y":-13.71,"rotation":74.93,"width":76,"height":99}},"NIco_big_0009_binjiao":{"NIco_big_0009_binjiao":{"x":48.53,"y":21.65,"rotation":112.99,"width":100,"height":140}},"NIco_big_0010_binjiao2":{"NIco_big_0010_binjiao2":{"x":44,"y":15.11,"rotation":91.17,"width":54,"height":136}},"NIco_big_0011_meimao":{"NIco_big_0011_meimao":{"x":-2.68,"y":-20.09,"scaleX":-0.865,"rotation":-91.34,"width":33,"height":11}},"NIco_big_0011_meimao2":{"NIco_big_0011_meimao":{"x":0.64,"y":27.24,"rotation":-91.34,"width":33,"height":11}},"NIco_big_0015_kouxing01":{"NIco_big_0015_kouxing01":{"rotation":-91.34,"width":32,"height":17},"NIco_big_0014_kouxing02":{"rotation":-91.34,"width":36,"height":18},"NIco_big_0013_kouxing03":{"rotation":-91.34,"width":36,"height":20},"NIco_big_0012_kouxing04":{"rotation":-91.34,"width":30,"height":21}},"NIco_big_0019_yanqiu":{"NIco_big_0019_yanqiu":{"x":-2.44,"y":-176.07,"rotation":-91.34,"width":22,"height":22}},"NIco_big_0019_yanqiu2":{"NIco_big_0019_yanqiu":{"x":-0.11,"y":-126.36,"rotation":-91.34,"width":22,"height":22}},"NIco_big_0023_waiyiyou":{"NIco_big_0023_waiyiyou":{"x":21.15,"y":1.03,"rotation":101.05,"width":27,"height":69}},"NIco_big_0024_youtui":{"NIco_big_0024_youtui":{"x":86.86,"y":-3.89,"rotation":87.44,"width":44,"height":232}},"NIco_big_0025_kua":{"NIco_big_0025_kua":{"x":-5.23,"y":4.57,"width":94,"height":61}},"NIco_big_0026_zuotui":{"NIco_big_0026_zuotui":{"x":84.57,"y":-2.55,"rotation":92.7,"width":49,"height":243}},"NIco_big_0027_xiong":{"NIco_big_0027_xiong":{"x":23.59,"y":-6.47,"rotation":-92.71,"width":63,"height":72}},"NIco_big_0028_shentixia":{"NIco_big_0028_shentixia":{"x":19.75,"y":3.53,"rotation":-91.8,"width":71,"height":67}},"NIco_big_0029_waiyizuo":{"NIco_big_0029_waiyizuo":{"x":19.06,"y":-4.63,"rotation":78.29,"width":47,"height":68}},"NIco_big_0030_toufa":{"NIco_big_0030_toufa":{"x":49.61,"y":11.98,"rotation":-91.34,"width":155,"height":140}},"bone4":{"NIco_big_0022_sijinhou":{"x":48.3,"y":33.13,"rotation":-92.71,"width":37,"height":28}},"bone42":{"NIco_big_0021_sijin":{"x":47.3,"y":1.87,"rotation":-92.71,"width":39,"height":28}},"bone5":{"NIco_big_0020_yanbai":{"x":52.18,"y":-2.15,"rotation":-91.34,"width":83,"height":38}},"bone52":{"NIco_big_0018_lian":{"x":55.64,"y":3.65,"rotation":-91.34,"width":101,"height":120}},"bone53":{"NIco_big_0016_biyan":{"x":52.42,"y":-1.23,"rotation":-91.34,"width":82,"height":37},"NIco_big_0017_yan":{"x":51.88,"y":-2.36,"rotation":-91.34,"width":85,"height":37}},"bone54":{"NIco_big_0031_maozihou":{"x":84.27,"y":5.73,"rotation":-91.34,"width":252,"height":130}},"bone55":{"NIco_big_0007_maoziqian":{"x":118.34,"y":2.49,"rotation":-91.34,"width":242,"height":103}}}},"animations":{"idle_01":{"bones":{"root":{"rotate":[{"time":0,"angle":0,"curve":"stepped"},{"time":5.3333,"angle":0,"curve":"stepped"},{"time":5.8,"angle":0,"curve":"stepped"},{"time":6,"angle":0,"curve":"stepped"},{"time":7,"angle":0,"curve":"stepped"},{"time":8,"angle":0,"curve":"stepped"},{"time":9,"angle":0,"curve":"stepped"},{"time":10,"angle":0,"curve":"stepped"},{"time":11,"angle":0,"curve":"stepped"},{"time":12,"angle":0}],"translate":[{"time":0,"x":0,"y":0,"curve":"stepped"},{"time":5.3333,"x":0,"y":0,"curve":"stepped"},{"time":5.8,"x":0,"y":0,"curve":"stepped"},{"time":6,"x":0,"y":0,"curve":"stepped"},{"time":7,"x":0,"y":0,"curve":"stepped"},{"time":8,"x":0,"y":0,"curve":"stepped"},{"time":9,"x":0,"y":0,"curve":"stepped"},{"time":10,"x":0,"y":0,"curve":"stepped"},{"time":11,"x":0,"y":0,"curve":"stepped"},{"time":12,"x":0,"y":0}],"scale":[{"time":0,"x":1,"y":1,"curve":"stepped"},{"time":5.3333,"x":1,"y":1,"curve":"stepped"},{"time":5.8,"x":1,"y":1,"curve":"stepped"},{"time":6,"x":1,"y":1,"curve":"stepped"},{"time":7,"x":1,"y":1,"curve":"stepped"},{"time":8,"x":1,"y":1,"curve":"stepped"},{"time":9,"x":1,"y":1,"curve":"stepped"},{"time":10,"x":1,"y":1,"curve":"stepped"},{"time":11,"x":1,"y":1,"curve":"stepped"},{"time":12,"x":1,"y":1}]},"bone":{"rotate":[{"time":0,"angle":0,"curve":"stepped"},{"time":5.3333,"angle":0,"curve":"stepped"},{"time":5.8,"angle":0,"curve":"stepped"},{"time":6,"angle":0,"curve":"stepped"},{"time":7,"angle":0,"curve":"stepped"},{"time":8,"angle":0,"curve":"stepped"},{"time":9,"angle":0,"curve":"stepped"},{"time":10,"angle":0,"curve":"stepped"},{"time":11,"angle":0,"curve":"stepped"},{"time":12,"angle":0}],"translate":[{"time":0,"x":0,"y":0,"curve":"stepped"},{"time":0.3333,"x":0,"y":0},{"time":0.6666,"x":-15.37,"y":0,"curve":"stepped"},{"time":5.3333,"x":-15.37,"y":0},{"time":5.8,"x":0,"y":0,"curve":"stepped"},{"time":6,"x":0,"y":0,"curve":"stepped"},{"time":7,"x":0,"y":0,"curve":"stepped"},{"time":8,"x":0,"y":0,"curve":"stepped"},{"time":9,"x":0,"y":0,"curve":"stepped"},{"time":10,"x":0,"y":0,"curve":"stepped"},{"time":11,"x":0,"y":0,"curve":"stepped"},{"time":12,"x":0,"y":0}],"scale":[{"time":0,"x":1,"y":1,"curve":"stepped"},{"time":5.3333,"x":1,"y":1,"curve":"stepped"},{"time":5.8,"x":1,"y":1,"curve":"stepped"},{"time":6,"x":1,"y":1,"curve":"stepped"},{"time":7,"x":1,"y":1,"curve":"stepped"},{"time":8,"x":1,"y":1,"curve":"stepped"},{"time":9,"x":1,"y":1,"curve":"stepped"},{"time":10,"x":1,"y":1,"curve":"stepped"},{"time":11,"x":1,"y":1,"curve":"stepped"},{"time":12,"x":1,"y":1}]},"bone17":{"rotate":[{"time":0,"angle":0,"curve":"stepped"},{"time":0.3333,"angle":0},{"time":0.4333,"angle":0.96},{"time":0.6666,"angle":-2.63,"curve":"stepped"},{"time":5.3333,"angle":-2.63},{"time":5.8,"angle":0,"curve":"stepped"},{"time":6,"angle":0,"curve":"stepped"},{"time":7,"angle":0,"curve":"stepped"},{"time":8,"angle":0,"curve":"stepped"},{"time":9,"angle":0,"curve":"stepped"},{"time":10,"angle":0,"curve":"stepped"},{"time":11,"angle":0,"curve":"stepped"},{"time":12,"angle":0}],"translate":[{"time":0,"x":0,"y":0,"curve":"stepped"},{"time":5.3333,"x":0,"y":0,"curve":"stepped"},{"time":5.8,"x":0,"y":0,"curve":"stepped"},{"time":6,"x":0,"y":0,"curve":"stepped"},{"time":7,"x":0,"y":0,"curve":"stepped"},{"time":8,"x":0,"y":0,"curve":"stepped"},{"time":9,"x":0,"y":0,"curve":"stepped"},{"time":10,"x":0,"y":0,"curve":"stepped"},{"time":11,"x":0,"y":0,"curve":"stepped"},{"time":12,"x":0,"y":0}],"scale":[{"time":0,"x":1,"y":1,"curve":"stepped"},{"time":5.3333,"x":1,"y":1,"curve":"stepped"},{"time":5.8,"x":1,"y":1,"curve":"stepped"},{"time":6,"x":1,"y":1,"curve":"stepped"},{"time":7,"x":1,"y":1,"curve":"stepped"},{"time":8,"x":1,"y":1,"curve":"stepped"},{"time":9,"x":1,"y":1,"curve":"stepped"},{"time":10,"x":1,"y":1,"curve":"stepped"},{"time":11,"x":1,"y":1,"curve":"stepped"},{"time":12,"x":1,"y":1}]},"bone2":{"rotate":[{"time":0,"angle":0,"curve":"stepped"},{"time":0.3333,"angle":0},{"time":0.6666,"angle":5.13,"curve":"stepped"},{"time":5.3333,"angle":5.13},{"time":5.8,"angle":0,"curve":"stepped"},{"time":6,"angle":0,"curve":"stepped"},{"time":7,"angle":0,"curve":"stepped"},{"time":8,"angle":0,"curve":"stepped"},{"time":9,"angle":0,"curve":"stepped"},{"time":10,"angle":0,"curve":"stepped"},{"time":11,"angle":0,"curve":"stepped"},{"time":12,"angle":0}],"translate":[{"time":0,"x":0,"y":0,"curve":"stepped"},{"time":0.3333,"x":0,"y":0},{"time":0.6666,"x":1.45,"y":0.11,"curve":"stepped"},{"time":5.3333,"x":1.45,"y":0.11},{"time":5.8,"x":0,"y":0,"curve":"stepped"},{"time":6,"x":0,"y":0,"curve":"stepped"},{"time":7,"x":0,"y":0,"curve":"stepped"},{"time":8,"x":0,"y":0,"curve":"stepped"},{"time":9,"x":0,"y":0,"curve":"stepped"},{"time":10,"x":0,"y":0,"curve":"stepped"},{"time":11,"x":0,"y":0,"curve":"stepped"},{"time":12,"x":0,"y":0}],"scale":[{"time":0,"x":1,"y":1,"curve":"stepped"},{"time":5.3333,"x":1,"y":1,"curve":"stepped"},{"time":5.8,"x":1,"y":1,"curve":"stepped"},{"time":6,"x":1,"y":1,"curve":"stepped"},{"time":7,"x":1,"y":1,"curve":"stepped"},{"time":8,"x":1,"y":1,"curve":"stepped"},{"time":9,"x":1,"y":1,"curve":"stepped"},{"time":10,"x":1,"y":1,"curve":"stepped"},{"time":11,"x":1,"y":1,"curve":"stepped"},{"time":12,"x":1,"y":1}]},"bone3":{"rotate":[{"time":0,"angle":0},{"time":0.3333,"angle":-1.38},{"time":0.6666,"angle":5.5,"curve":"stepped"},{"time":1.3333,"angle":5.5,"curve":"stepped"},{"time":3.3333,"angle":5.5,"curve":"stepped"},{"time":5.3333,"angle":5.5},{"time":5.8,"angle":0,"curve":"stepped"},{"time":6,"angle":0,"curve":"stepped"},{"time":7,"angle":0,"curve":"stepped"},{"time":8,"angle":0,"curve":"stepped"},{"time":9,"angle":0,"curve":"stepped"},{"time":10,"angle":0,"curve":"stepped"},{"time":11,"angle":0,"curve":"stepped"},{"time":12,"angle":0}],"translate":[{"time":0,"x":0,"y":0,"curve":"stepped"},{"time":1.3333,"x":0,"y":0,"curve":[0.25,0,0.75,1]},{"time":2.3333,"x":-0.08,"y":0.94},{"time":3.3333,"x":0,"y":0,"curve":[0.25,0,0.75,1]},{"time":4.3333,"x":-0.08,"y":0.94},{"time":5.3333,"x":0,"y":0,"curve":"stepped"},{"time":5.8,"x":0,"y":0,"curve":"stepped"},{"time":6,"x":0,"y":0},{"time":7,"x":-0.08,"y":0.94},{"time":8,"x":0,"y":0},{"time":9,"x":-0.08,"y":0.94},{"time":10,"x":0,"y":0},{"time":11,"x":-0.08,"y":0.94},{"time":12,"x":0,"y":0}],"scale":[{"time":0,"x":1,"y":1,"curve":"stepped"},{"time":1.3333,"x":1,"y":1,"curve":"stepped"},{"time":3.3333,"x":1,"y":1,"curve":"stepped"},{"time":5.3333,"x":1,"y":1,"curve":"stepped"},{"time":5.8,"x":1,"y":1,"curve":"stepped"},{"time":6,"x":1,"y":1,"curve":"stepped"},{"time":7,"x":1,"y":1,"curve":"stepped"},{"time":8,"x":1,"y":1,"curve":"stepped"},{"time":9,"x":1,"y":1,"curve":"stepped"},{"time":10,"x":1,"y":1,"curve":"stepped"},{"time":11,"x":1,"y":1,"curve":"stepped"},{"time":12,"x":1,"y":1}]},"bone4":{"rotate":[{"time":0,"angle":0,"curve":"stepped"},{"time":5.3333,"angle":0,"curve":"stepped"},{"time":5.5666,"angle":0,"curve":"stepped"},{"time":5.8333,"angle":0,"curve":"stepped"},{"time":6.1333,"angle":0,"curve":"stepped"},{"time":6.4333,"angle":0,"curve":"stepped"},{"time":7.1666,"angle":0,"curve":"stepped"},{"time":8,"angle":0,"curve":"stepped"},{"time":9.1666,"angle":0,"curve":"stepped"},{"time":10,"angle":0,"curve":"stepped"},{"time":11.1666,"angle":0,"curve":"stepped"},{"time":12,"angle":0}],"translate":[{"time":0,"x":0,"y":0,"curve":"stepped"},{"time":0.3333,"x":0,"y":0},{"time":0.6666,"x":-1.76,"y":-2.27},{"time":0.9333,"x":1.67,"y":1.74},{"time":1.2,"x":-1.26,"y":-0.32},{"time":1.5,"x":0,"y":0,"curve":"stepped"},{"time":3.5,"x":0,"y":0,"curve":"stepped"},{"time":5.3333,"x":0,"y":0},{"time":5.5666,"x":0.05,"y":3.2},{"time":5.8333,"x":-0.02,"y":-1.87},{"time":6.1333,"x":0.01,"y":0.99},{"time":6.4333,"x":0,"y":0,"curve":[0.272,0,0.619,0.4]},{"time":6.6333,"x":0.18,"y":0,"curve":[0.338,0.35,0.757,1]},{"time":7.1666,"x":1.08,"y":-0.01,"curve":[0.271,0,0.619,0.4]},{"time":7.4,"x":1.02,"y":-0.01,"curve":[0.34,0.35,0.757,1]},{"time":8,"x":0,"y":0},{"time":8.2333,"x":0.18,"y":0,"curve":[0.338,0.35,0.757,1]},{"time":9.1666,"x":1.14,"y":-0.01,"curve":[0.25,0,0.75,1]},{"time":10,"x":0,"y":0,"curve":[0.25,0,0.75,1]},{"time":11.1666,"x":1.14,"y":-0.01,"curve":[0.25,0,0.75,1]},{"time":12,"x":0,"y":0}],"scale":[{"time":0,"x":1,"y":1,"curve":"stepped"},{"time":0.3333,"x":1,"y":1},{"time":0.6666,"x":1.057,"y":1},{"time":0.9333,"x":0.998,"y":1},{"time":1.2,"x":1.025,"y":1},{"time":1.5,"x":1,"y":1,"curve":"stepped"},{"time":3.5,"x":1,"y":1,"curve":"stepped"},{"time":5.3333,"x":1,"y":1,"curve":"stepped"},{"time":5.5666,"x":1,"y":1},{"time":5.8333,"x":1.026,"y":1},{"time":6.1333,"x":0.984,"y":1},{"time":6.4333,"x":1,"y":1,"curve":"stepped"},{"time":7.1666,"x":1,"y":1,"curve":"stepped"},{"time":8,"x":1,"y":1,"curve":"stepped"},{"time":9.1666,"x":1,"y":1,"curve":"stepped"},{"time":10,"x":1,"y":1,"curve":"stepped"},{"time":11.1666,"x":1,"y":1,"curve":"stepped"},{"time":12,"x":1,"y":1}]},"bone6":{"rotate":[{"time":0,"angle":0},{"time":0.3333,"angle":-26.59},{"time":0.4333,"angle":-15.2},{"time":0.6666,"angle":-334.86},{"time":5.3333,"angle":25.13},{"time":5.8,"angle":0,"curve":"stepped"},{"time":6,"angle":0,"curve":[0.25,0,0.75,1]},{"time":7,"angle":1.29,"curve":[0.25,0,0.75,1]},{"time":8,"angle":0,"curve":[0.25,0,0.75,1]},{"time":9,"angle":1.29,"curve":[0.25,0,0.75,1]},{"time":10,"angle":0,"curve":[0.25,0,0.75,1]},{"time":11,"angle":1.29,"curve":[0.25,0,0.75,1]},{"time":12,"angle":0}],"translate":[{"time":0,"x":0,"y":0,"curve":"stepped"},{"time":0.3333,"x":0,"y":0},{"time":0.6666,"x":-5.58,"y":-0.21,"curve":"stepped"},{"time":5.3333,"x":-5.58,"y":-0.21},{"time":5.8,"x":0,"y":0,"curve":"stepped"},{"time":6,"x":0,"y":0,"curve":"stepped"},{"time":7,"x":0,"y":0,"curve":"stepped"},{"time":8,"x":0,"y":0,"curve":"stepped"},{"time":9,"x":0,"y":0,"curve":"stepped"},{"time":10,"x":0,"y":0,"curve":"stepped"},{"time":11,"x":0,"y":0,"curve":"stepped"},{"time":12,"x":0,"y":0}],"scale":[{"time":0,"x":1,"y":1,"curve":"stepped"},{"time":5.3333,"x":1,"y":1,"curve":"stepped"},{"time":5.8,"x":1,"y":1,"curve":"stepped"},{"time":6,"x":1,"y":1,"curve":"stepped"},{"time":7,"x":1,"y":1,"curve":"stepped"},{"time":8,"x":1,"y":1,"curve":"stepped"},{"time":9,"x":1,"y":1,"curve":"stepped"},{"time":10,"x":1,"y":1,"curve":"stepped"},{"time":11,"x":1,"y":1,"curve":"stepped"},{"time":12,"x":1,"y":1}]},"bone9":{"rotate":[{"time":0,"angle":0},{"time":0.3333,"angle":3.66},{"time":0.6666,"angle":-4.57,"curve":"stepped"},{"time":5.3333,"angle":-4.57},{"time":5.8,"angle":0,"curve":"stepped"},{"time":6,"angle":0,"curve":[0.25,0,0.75,1]},{"time":7,"angle":-0.25,"curve":[0.25,0,0.75,1]},{"time":8,"angle":0,"curve":[0.25,0,0.75,1]},{"time":9,"angle":-0.25,"curve":[0.25,0,0.75,1]},{"time":10,"angle":0,"curve":[0.25,0,0.75,1]},{"time":11,"angle":-0.25,"curve":[0.25,0,0.75,1]},{"time":12,"angle":0}],"translate":[{"time":0,"x":0,"y":0},{"time":0.6666,"x":0.46,"y":0.16,"curve":"stepped"},{"time":5.3333,"x":0.46,"y":0.16},{"time":5.8,"x":0,"y":0,"curve":"stepped"},{"time":6,"x":0,"y":0,"curve":"stepped"},{"time":7,"x":0,"y":0,"curve":"stepped"},{"time":8,"x":0,"y":0,"curve":"stepped"},{"time":9,"x":0,"y":0,"curve":"stepped"},{"time":10,"x":0,"y":0,"curve":"stepped"},{"time":11,"x":0,"y":0,"curve":"stepped"},{"time":12,"x":0,"y":0}],"scale":[{"time":0,"x":1,"y":1,"curve":"stepped"},{"time":5.3333,"x":1,"y":1,"curve":"stepped"},{"time":5.8,"x":1,"y":1,"curve":"stepped"},{"time":6,"x":1,"y":1,"curve":"stepped"},{"time":7,"x":1,"y":1,"curve":"stepped"},{"time":8,"x":1,"y":1,"curve":"stepped"},{"time":9,"x":1,"y":1,"curve":"stepped"},{"time":10,"x":1,"y":1,"curve":"stepped"},{"time":11,"x":1,"y":1,"curve":"stepped"},{"time":12,"x":1,"y":1}]},"bone10":{"rotate":[{"time":0,"angle":-9.91},{"time":0.3333,"angle":-15.13},{"time":0.6666,"angle":21.07,"curve":"stepped"},{"time":5.3333,"angle":21.07},{"time":5.5333,"angle":21.06},{"time":5.8333,"angle":-9.91,"curve":"stepped"},{"time":6,"angle":-9.91,"curve":[0.25,0,0.75,1]},{"time":7,"angle":-15.51,"curve":[0.25,0,0.75,1]},{"time":8,"angle":-9.91,"curve":[0.25,0,0.75,1]},{"time":9,"angle":-12.86,"curve":[0.25,0,0.75,1]},{"time":10,"angle":-9.91,"curve":[0.25,0,0.75,1]},{"time":11,"angle":-12.86,"curve":[0.25,0,0.75,1]},{"time":12,"angle":-9.91}],"translate":[{"time":0,"x":0,"y":0,"curve":"stepped"},{"time":0.3333,"x":0,"y":0},{"time":0.6666,"x":1.35,"y":0.37,"curve":"stepped"},{"time":5.3333,"x":1.35,"y":0.37},{"time":5.8333,"x":0,"y":0,"curve":"stepped"},{"time":6,"x":0,"y":0,"curve":"stepped"},{"time":7,"x":0,"y":0,"curve":"stepped"},{"time":8,"x":0,"y":0,"curve":"stepped"},{"time":9,"x":0,"y":0,"curve":"stepped"},{"time":10,"x":0,"y":0,"curve":"stepped"},{"time":11,"x":0,"y":0,"curve":"stepped"},{"time":12,"x":0,"y":0}],"scale":[{"time":0,"x":1,"y":1,"curve":"stepped"},{"time":5.3333,"x":1,"y":1,"curve":"stepped"},{"time":5.8333,"x":1,"y":1,"curve":"stepped"},{"time":6,"x":1,"y":1,"curve":"stepped"},{"time":7,"x":1,"y":1,"curve":"stepped"},{"time":8,"x":1,"y":1,"curve":"stepped"},{"time":9,"x":1,"y":1,"curve":"stepped"},{"time":10,"x":1,"y":1,"curve":"stepped"},{"time":11,"x":1,"y":1,"curve":"stepped"},{"time":12,"x":1,"y":1}]},"bone18":{"rotate":[{"time":0,"angle":0,"curve":"stepped"},{"time":0.1333,"angle":0},{"time":0.3333,"angle":-6.42},{"time":0.8,"angle":11.5},{"time":1.2,"angle":1.83},{"time":1.6666,"angle":2.72,"curve":"stepped"},{"time":5.3333,"angle":2.72},{"time":5.8,"angle":0,"curve":"stepped"},{"time":6,"angle":0,"curve":"stepped"},{"time":7,"angle":0,"curve":"stepped"},{"time":8,"angle":0,"curve":"stepped"},{"time":9,"angle":0,"curve":"stepped"},{"time":10,"angle":0,"curve":"stepped"},{"time":11,"angle":0,"curve":"stepped"},{"time":12,"angle":0}],"translate":[{"time":0,"x":0,"y":0,"curve":"stepped"},{"time":5.3333,"x":0,"y":0,"curve":"stepped"},{"time":5.8,"x":0,"y":0,"curve":"stepped"},{"time":6,"x":0,"y":0,"curve":"stepped"},{"time":7,"x":0,"y":0,"curve":"stepped"},{"time":8,"x":0,"y":0,"curve":"stepped"},{"time":9,"x":0,"y":0,"curve":"stepped"},{"time":10,"x":0,"y":0,"curve":"stepped"},{"time":11,"x":0,"y":0,"curve":"stepped"},{"time":12,"x":0,"y":0}],"scale":[{"time":0,"x":1,"y":1,"curve":"stepped"},{"time":5.3333,"x":1,"y":1,"curve":"stepped"},{"time":5.8,"x":1,"y":1,"curve":"stepped"},{"time":6,"x":1,"y":1,"curve":"stepped"},{"time":7,"x":1,"y":1,"curve":"stepped"},{"time":8,"x":1,"y":1,"curve":"stepped"},{"time":9,"x":1,"y":1,"curve":"stepped"},{"time":10,"x":1,"y":1,"curve":"stepped"},{"time":11,"x":1,"y":1,"curve":"stepped"},{"time":12,"x":1,"y":1}]},"bone19":{"rotate":[{"time":0,"angle":0,"curve":"stepped"},{"time":0.1333,"angle":0},{"time":0.3333,"angle":5.53},{"time":0.8,"angle":-2.55},{"time":1.2,"angle":2.39},{"time":1.6666,"angle":-0.79,"curve":"stepped"},{"time":5.3333,"angle":-0.79},{"time":5.8,"angle":0,"curve":"stepped"},{"time":6,"angle":0,"curve":"stepped"},{"time":7,"angle":0,"curve":"stepped"},{"time":8,"angle":0,"curve":"stepped"},{"time":9,"angle":0,"curve":"stepped"},{"time":10,"angle":0,"curve":"stepped"},{"time":11,"angle":0,"curve":"stepped"},{"time":12,"angle":0}],"translate":[{"time":0,"x":0,"y":0,"curve":"stepped"},{"time":5.3333,"x":0,"y":0,"curve":"stepped"},{"time":5.8,"x":0,"y":0,"curve":"stepped"},{"time":6,"x":0,"y":0,"curve":"stepped"},{"time":7,"x":0,"y":0,"curve":"stepped"},{"time":8,"x":0,"y":0,"curve":"stepped"},{"time":9,"x":0,"y":0,"curve":"stepped"},{"time":10,"x":0,"y":0,"curve":"stepped"},{"time":11,"x":0,"y":0,"curve":"stepped"},{"time":12,"x":0,"y":0}],"scale":[{"time":0,"x":1,"y":1,"curve":"stepped"},{"time":5.3333,"x":1,"y":1,"curve":"stepped"},{"time":5.8,"x":1,"y":1,"curve":"stepped"},{"time":6,"x":1,"y":1,"curve":"stepped"},{"time":7,"x":1,"y":1,"curve":"stepped"},{"time":8,"x":1,"y":1,"curve":"stepped"},{"time":9,"x":1,"y":1,"curve":"stepped"},{"time":10,"x":1,"y":1,"curve":"stepped"},{"time":11,"x":1,"y":1,"curve":"stepped"},{"time":12,"x":1,"y":1}]},"bone5":{"rotate":[{"time":0,"angle":0},{"time":0.4333,"angle":-5.3},{"time":0.8333,"angle":6.84},{"time":1.4,"angle":6.98},{"time":2.2333,"angle":6.74},{"time":2.7333,"angle":5.85},{"time":3.4333,"angle":6.84},{"time":4,"angle":6.98},{"time":4.6666,"angle":6.74},{"time":5.3333,"angle":5.85},{"time":5.5333,"angle":8.72},{"time":5.9,"angle":0,"curve":"stepped"},{"time":6,"angle":0,"curve":"stepped"},{"time":7,"angle":0,"curve":"stepped"},{"time":8,"angle":0,"curve":"stepped"},{"time":9,"angle":0,"curve":"stepped"},{"time":10,"angle":0,"curve":"stepped"},{"time":11,"angle":0,"curve":"stepped"},{"time":12,"angle":0}],"translate":[{"time":0,"x":0,"y":0},{"time":0.8333,"x":-1.1,"y":0.89},{"time":2.2333,"x":2.62,"y":0.25},{"time":5.3333,"x":0,"y":0,"curve":"stepped"},{"time":5.9,"x":0,"y":0,"curve":"stepped"},{"time":6,"x":0,"y":0,"curve":"stepped"},{"time":7,"x":0,"y":0,"curve":"stepped"},{"time":8,"x":0,"y":0,"curve":"stepped"},{"time":9,"x":0,"y":0,"curve":"stepped"},{"time":10,"x":0,"y":0,"curve":"stepped"},{"time":11,"x":0,"y":0,"curve":"stepped"},{"time":12,"x":0,"y":0}],"scale":[{"time":0,"x":1,"y":1,"curve":"stepped"},{"time":5.3333,"x":1,"y":1,"curve":"stepped"},{"time":5.9,"x":1,"y":1,"curve":"stepped"},{"time":6,"x":1,"y":1,"curve":"stepped"},{"time":7,"x":1,"y":1,"curve":"stepped"},{"time":8,"x":1,"y":1,"curve":"stepped"},{"time":9,"x":1,"y":1,"curve":"stepped"},{"time":10,"x":1,"y":1,"curve":"stepped"},{"time":11,"x":1,"y":1,"curve":"stepped"},{"time":12,"x":1,"y":1}]},"bone7":{"rotate":[{"time":0,"angle":0},{"time":0.1333,"angle":9.69},{"time":0.3333,"angle":12.33},{"time":0.4333,"angle":-4.41},{"time":0.4666,"angle":-4.71},{"time":0.6666,"angle":-0.25,"curve":"stepped"},{"time":5.3333,"angle":-0.25},{"time":5.5333,"angle":16.13},{"time":5.8,"angle":0,"curve":"stepped"},{"time":6,"angle":0,"curve":"stepped"},{"time":7,"angle":0,"curve":"stepped"},{"time":8,"angle":0,"curve":"stepped"},{"time":9,"angle":0,"curve":"stepped"},{"time":10,"angle":0,"curve":"stepped"},{"time":11,"angle":0,"curve":"stepped"},{"time":12,"angle":0}],"translate":[{"time":0,"x":0,"y":0},{"time":0.1333,"x":0.25,"y":-2.57,"curve":"stepped"},{"time":5.3333,"x":0.25,"y":-2.57},{"time":5.8,"x":0,"y":0,"curve":"stepped"},{"time":6,"x":0,"y":0,"curve":"stepped"},{"time":7,"x":0,"y":0,"curve":"stepped"},{"time":8,"x":0,"y":0,"curve":"stepped"},{"time":9,"x":0,"y":0,"curve":"stepped"},{"time":10,"x":0,"y":0,"curve":"stepped"},{"time":11,"x":0,"y":0,"curve":"stepped"},{"time":12,"x":0,"y":0}],"scale":[{"time":0,"x":1,"y":1,"curve":"stepped"},{"time":5.3333,"x":1,"y":1,"curve":"stepped"},{"time":5.8,"x":1,"y":1,"curve":"stepped"},{"time":6,"x":1,"y":1,"curve":"stepped"},{"time":7,"x":1,"y":1,"curve":"stepped"},{"time":8,"x":1,"y":1,"curve":"stepped"},{"time":9,"x":1,"y":1,"curve":"stepped"},{"time":10,"x":1,"y":1,"curve":"stepped"},{"time":11,"x":1,"y":1,"curve":"stepped"},{"time":12,"x":1,"y":1}]},"bone11":{"rotate":[{"time":0,"angle":0},{"time":0.3333,"angle":-17.74},{"time":0.4666,"angle":-63.84},{"time":0.7666,"angle":-10.14,"curve":"stepped"},{"time":5.3333,"angle":-10.14,"curve":[0.25,0,0.75,1]},{"time":5.5333,"angle":11.81,"curve":[0.25,0,0.75,1]},{"time":6,"angle":0},{"time":6.4,"angle":3.17},{"time":7,"angle":0},{"time":7.5,"angle":-2.86},{"time":8,"angle":0},{"time":8.3333,"angle":3.17},{"time":9,"angle":0},{"time":9.4333,"angle":-2.86},{"time":10,"angle":0,"curve":"stepped"},{"time":11,"angle":0,"curve":"stepped"},{"time":12,"angle":0}],"translate":[{"time":0,"x":0,"y":0},{"time":0.4666,"x":2.5,"y":3.56},{"time":0.7666,"x":0.28,"y":0.52,"curve":"stepped"},{"time":5.3333,"x":0.28,"y":0.52,"curve":[0.25,0,0.75,1]},{"time":6,"x":0,"y":0,"curve":"stepped"},{"time":7,"x":0,"y":0,"curve":"stepped"},{"time":8,"x":0,"y":0,"curve":"stepped"},{"time":9,"x":0,"y":0,"curve":"stepped"},{"time":10,"x":0,"y":0,"curve":"stepped"},{"time":11,"x":0,"y":0,"curve":"stepped"},{"time":12,"x":0,"y":0}],"scale":[{"time":0,"x":1,"y":1,"curve":"stepped"},{"time":5.3333,"x":1,"y":1,"curve":"stepped"},{"time":6,"x":1,"y":1,"curve":"stepped"},{"time":7,"x":1,"y":1,"curve":"stepped"},{"time":8,"x":1,"y":1,"curve":"stepped"},{"time":9,"x":1,"y":1,"curve":"stepped"},{"time":10,"x":1,"y":1,"curve":"stepped"},{"time":11,"x":1,"y":1,"curve":"stepped"},{"time":12,"x":1,"y":1}]},"bone12":{"rotate":[{"time":0,"angle":0,"curve":"stepped"},{"time":5.3333,"angle":0,"curve":"stepped"},{"time":5.8,"angle":0,"curve":"stepped"},{"time":6,"angle":0}],"translate":[{"time":0,"x":0,"y":0,"curve":"stepped"},{"time":0.2,"x":0,"y":0},{"time":0.3333,"x":-2.25,"y":0,"curve":"stepped"},{"time":0.4666,"x":-2.25,"y":0},{"time":0.6,"x":0.77,"y":0,"curve":"stepped"},{"time":2.0333,"x":0.77,"y":0},{"time":2.1666,"x":-2.25,"y":0,"curve":"stepped"},{"time":2.3,"x":-2.25,"y":0},{"time":2.4333,"x":0.77,"y":0,"curve":"stepped"},{"time":5.3333,"x":0.77,"y":0,"curve":"stepped"},{"time":5.5666,"x":0.77,"y":0,"curve":"stepped"},{"time":5.6666,"x":0.77,"y":0},{"time":5.7333,"x":-2.25,"y":0,"curve":"stepped"},{"time":5.8666,"x":-2.25,"y":0},{"time":6,"x":0.77,"y":0,"curve":"stepped"},{"time":7.9,"x":0.77,"y":0},{"time":8,"x":-2.25,"y":0,"curve":"stepped"},{"time":8.1,"x":-2.25,"y":0},{"time":8.2,"x":0.77,"y":0}],"scale":[{"time":0,"x":1,"y":1,"curve":"stepped"},{"time":5.3333,"x":1,"y":1,"curve":"stepped"},{"time":5.8,"x":1,"y":1,"curve":"stepped"},{"time":6,"x":1,"y":1}]},"bone13":{"rotate":[{"time":0,"angle":0,"curve":"stepped"},{"time":5.3333,"angle":0,"curve":"stepped"},{"time":5.8,"angle":0,"curve":"stepped"},{"time":6,"angle":0,"curve":"stepped"},{"time":7,"angle":0,"curve":"stepped"},{"time":8,"angle":0,"curve":"stepped"},{"time":9,"angle":0,"curve":"stepped"},{"time":10,"angle":0,"curve":"stepped"},{"time":11,"angle":0,"curve":"stepped"},{"time":12,"angle":0}],"translate":[{"time":0,"x":0,"y":0,"curve":"stepped"},{"time":5.3333,"x":0,"y":0,"curve":"stepped"},{"time":5.8,"x":0,"y":0,"curve":"stepped"},{"time":6,"x":0,"y":0,"curve":"stepped"},{"time":7,"x":0,"y":0,"curve":"stepped"},{"time":8,"x":0,"y":0,"curve":"stepped"},{"time":9,"x":0,"y":0,"curve":"stepped"},{"time":10,"x":0,"y":0,"curve":"stepped"},{"time":11,"x":0,"y":0,"curve":"stepped"},{"time":12,"x":0,"y":0}],"scale":[{"time":0,"x":1,"y":1,"curve":"stepped"},{"time":5.3333,"x":1,"y":1,"curve":"stepped"},{"time":5.8,"x":1,"y":1,"curve":"stepped"},{"time":6,"x":1,"y":1,"curve":"stepped"},{"time":7,"x":1,"y":1,"curve":"stepped"},{"time":8,"x":1,"y":1,"curve":"stepped"},{"time":9,"x":1,"y":1,"curve":"stepped"},{"time":10,"x":1,"y":1,"curve":"stepped"},{"time":11,"x":1,"y":1,"curve":"stepped"},{"time":12,"x":1,"y":1}]},"bone14":{"rotate":[{"time":0,"angle":0},{"time":0.3333,"angle":-3.17,"curve":[0.25,0,0.75,1]},{"time":0.9333,"angle":2.18,"curve":[0.25,0,0.75,1]},{"time":1.3,"angle":-1.34,"curve":[0.25,0,0.75,1]},{"time":1.6333,"angle":0.88,"curve":[0.25,0,0.75,1]},{"time":1.9333,"angle":0,"curve":"stepped"},{"time":5.3333,"angle":0,"curve":"stepped"},{"time":5.8,"angle":0,"curve":"stepped"},{"time":6,"angle":0,"curve":"stepped"},{"time":7,"angle":0,"curve":"stepped"},{"time":8,"angle":0,"curve":"stepped"},{"time":9,"angle":0,"curve":"stepped"},{"time":10,"angle":0,"curve":"stepped"},{"time":11,"angle":0,"curve":"stepped"},{"time":12,"angle":0}],"translate":[{"time":0,"x":0,"y":0,"curve":"stepped"},{"time":5.3333,"x":0,"y":0,"curve":"stepped"},{"time":5.8,"x":0,"y":0,"curve":"stepped"},{"time":6,"x":0,"y":0,"curve":"stepped"},{"time":7,"x":0,"y":0,"curve":"stepped"},{"time":8,"x":0,"y":0,"curve":"stepped"},{"time":9,"x":0,"y":0,"curve":"stepped"},{"time":10,"x":0,"y":0,"curve":"stepped"},{"time":11,"x":0,"y":0,"curve":"stepped"},{"time":12,"x":0,"y":0}],"scale":[{"time":0,"x":1,"y":1,"curve":"stepped"},{"time":5.3333,"x":1,"y":1,"curve":"stepped"},{"time":5.8,"x":1,"y":1,"curve":"stepped"},{"time":6,"x":1,"y":1,"curve":"stepped"},{"time":7,"x":1,"y":1,"curve":"stepped"},{"time":8,"x":1,"y":1,"curve":"stepped"},{"time":9,"x":1,"y":1,"curve":"stepped"},{"time":10,"x":1,"y":1,"curve":"stepped"},{"time":11,"x":1,"y":1,"curve":"stepped"},{"time":12,"x":1,"y":1}]},"bone15":{"rotate":[{"time":0,"angle":0},{"time":0.3333,"angle":-2.49,"curve":[0.25,0,0.75,1]},{"time":0.9333,"angle":3.44,"curve":[0.25,0,0.75,1]},{"time":1.3,"angle":-2,"curve":[0.25,0,0.75,1]},{"time":1.6333,"angle":2.25,"curve":"stepped"},{"time":5.3333,"angle":2.25},{"time":5.8,"angle":0,"curve":"stepped"},{"time":6,"angle":0,"curve":"stepped"},{"time":7,"angle":0,"curve":"stepped"},{"time":8,"angle":0,"curve":"stepped"},{"time":9,"angle":0,"curve":"stepped"},{"time":10,"angle":0,"curve":"stepped"},{"time":11,"angle":0,"curve":"stepped"},{"time":12,"angle":0}],"translate":[{"time":0,"x":0,"y":0,"curve":"stepped"},{"time":5.3333,"x":0,"y":0,"curve":"stepped"},{"time":5.8,"x":0,"y":0,"curve":"stepped"},{"time":6,"x":0,"y":0,"curve":"stepped"},{"time":7,"x":0,"y":0,"curve":"stepped"},{"time":8,"x":0,"y":0,"curve":"stepped"},{"time":9,"x":0,"y":0,"curve":"stepped"},{"time":10,"x":0,"y":0,"curve":"stepped"},{"time":11,"x":0,"y":0,"curve":"stepped"},{"time":12,"x":0,"y":0}],"scale":[{"time":0,"x":1,"y":1,"curve":"stepped"},{"time":5.3333,"x":1,"y":1,"curve":"stepped"},{"time":5.8,"x":1,"y":1,"curve":"stepped"},{"time":6,"x":1,"y":1,"curve":"stepped"},{"time":7,"x":1,"y":1,"curve":"stepped"},{"time":8,"x":1,"y":1,"curve":"stepped"},{"time":9,"x":1,"y":1,"curve":"stepped"},{"time":10,"x":1,"y":1,"curve":"stepped"},{"time":11,"x":1,"y":1,"curve":"stepped"},{"time":12,"x":1,"y":1}]},"bone20":{"rotate":[{"time":0,"angle":0,"curve":"stepped"},{"time":5.7333,"angle":0,"curve":"stepped"},{"time":5.8333,"angle":0,"curve":"stepped"},{"time":7,"angle":0,"curve":"stepped"},{"time":8,"angle":0,"curve":"stepped"},{"time":9,"angle":0,"curve":"stepped"},{"time":10,"angle":0,"curve":"stepped"},{"time":11,"angle":0,"curve":"stepped"},{"time":12,"angle":0}],"translate":[{"time":0,"x":0,"y":0,"curve":"stepped"},{"time":0.5,"x":0,"y":0},{"time":0.6,"x":0,"y":-2,"curve":"stepped"},{"time":5.7333,"x":0,"y":-2},{"time":5.8333,"x":0,"y":0,"curve":"stepped"},{"time":7,"x":0,"y":0,"curve":"stepped"},{"time":8,"x":0,"y":0},{"time":8.1,"x":0,"y":-1.54,"curve":"stepped"},{"time":11.8666,"x":0,"y":-1.54},{"time":12,"x":0,"y":0}],"scale":[{"time":0,"x":1,"y":1,"curve":"stepped"},{"time":5.7333,"x":1,"y":1,"curve":"stepped"},{"time":5.8333,"x":1,"y":1,"curve":"stepped"},{"time":7,"x":1,"y":1,"curve":"stepped"},{"time":8,"x":1,"y":1,"curve":"stepped"},{"time":9,"x":1,"y":1,"curve":"stepped"},{"time":10,"x":1,"y":1,"curve":"stepped"},{"time":11,"x":1,"y":1,"curve":"stepped"},{"time":12,"x":1,"y":1}]},"bone8":{"rotate":[{"time":0,"angle":0},{"time":0.1333,"angle":34.32},{"time":0.3333,"angle":39},{"time":0.4333,"angle":8.24},{"time":0.6666,"angle":26.43},{"time":1.1333,"angle":45.62,"curve":"stepped"},{"time":5.3333,"angle":45.62},{"time":5.5333,"angle":28.52},{"time":5.8,"angle":0,"curve":"stepped"},{"time":6,"angle":0,"curve":"stepped"},{"time":7,"angle":0,"curve":"stepped"},{"time":8,"angle":0,"curve":"stepped"},{"time":9,"angle":0,"curve":"stepped"},{"time":10,"angle":0,"curve":"stepped"},{"time":11,"angle":0,"curve":"stepped"},{"time":12,"angle":0}],"translate":[{"time":0,"x":0,"y":0},{"time":0.1333,"x":-1.2,"y":2.46},{"time":0.3333,"x":-1.89,"y":3.83},{"time":0.6666,"x":-0.76,"y":2.44,"curve":"stepped"},{"time":5.3333,"x":-0.76,"y":2.44},{"time":5.8,"x":0,"y":0,"curve":"stepped"},{"time":6,"x":0,"y":0,"curve":"stepped"},{"time":7,"x":0,"y":0,"curve":"stepped"},{"time":8,"x":0,"y":0,"curve":"stepped"},{"time":9,"x":0,"y":0,"curve":"stepped"},{"time":10,"x":0,"y":0,"curve":"stepped"},{"time":11,"x":0,"y":0,"curve":"stepped"},{"time":12,"x":0,"y":0}],"scale":[{"time":0,"x":1,"y":1,"curve":"stepped"},{"time":5.3333,"x":1,"y":1,"curve":"stepped"},{"time":5.8,"x":1,"y":1,"curve":"stepped"},{"time":6,"x":1,"y":1,"curve":"stepped"},{"time":7,"x":1,"y":1,"curve":"stepped"},{"time":8,"x":1,"y":1,"curve":"stepped"},{"time":9,"x":1,"y":1,"curve":"stepped"},{"time":10,"x":1,"y":1,"curve":"stepped"},{"time":11,"x":1,"y":1,"curve":"stepped"},{"time":12,"x":1,"y":1}]},"bone16":{"rotate":[{"time":0,"angle":0},{"time":0.3333,"angle":-2.75,"curve":[0.25,0,0.75,1]},{"time":0.9333,"angle":1.31,"curve":[0.25,0,0.75,1]},{"time":1.3666,"angle":-2.14},{"time":1.6666,"angle":-1.2},{"time":2,"angle":-2.72,"curve":"stepped"},{"time":5.3333,"angle":-2.72},{"time":5.8,"angle":0,"curve":"stepped"},{"time":6,"angle":0,"curve":"stepped"},{"time":7,"angle":0,"curve":"stepped"},{"time":8,"angle":0,"curve":"stepped"},{"time":9,"angle":0,"curve":"stepped"},{"time":10,"angle":0,"curve":"stepped"},{"time":11,"angle":0,"curve":"stepped"},{"time":12,"angle":0}],"translate":[{"time":0,"x":0,"y":0,"curve":"stepped"},{"time":5.3333,"x":0,"y":0,"curve":"stepped"},{"time":5.8,"x":0,"y":0,"curve":"stepped"},{"time":6,"x":0,"y":0,"curve":"stepped"},{"time":7,"x":0,"y":0,"curve":"stepped"},{"time":8,"x":0,"y":0,"curve":"stepped"},{"time":9,"x":0,"y":0,"curve":"stepped"},{"time":10,"x":0,"y":0,"curve":"stepped"},{"time":11,"x":0,"y":0,"curve":"stepped"},{"time":12,"x":0,"y":0}],"scale":[{"time":0,"x":1,"y":1,"curve":"stepped"},{"time":5.3333,"x":1,"y":1,"curve":"stepped"},{"time":5.8,"x":1,"y":1,"curve":"stepped"},{"time":6,"x":1,"y":1,"curve":"stepped"},{"time":7,"x":1,"y":1,"curve":"stepped"},{"time":8,"x":1,"y":1,"curve":"stepped"},{"time":9,"x":1,"y":1,"curve":"stepped"},{"time":10,"x":1,"y":1,"curve":"stepped"},{"time":11,"x":1,"y":1,"curve":"stepped"},{"time":12,"x":1,"y":1}]},"bone21":{"rotate":[{"time":5.3333,"angle":0,"curve":"stepped"},{"time":6,"angle":0,"curve":"stepped"},{"time":8,"angle":0,"curve":"stepped"},{"time":10,"angle":0,"curve":"stepped"},{"time":12,"angle":0}],"translate":[{"time":1.3333,"x":0,"y":0},{"time":2.4333,"x":1.27,"y":0.02},{"time":3.3333,"x":0,"y":0},{"time":4.4333,"x":1.27,"y":0.02},{"time":5.3333,"x":0,"y":0,"curve":"stepped"},{"time":6,"x":0,"y":0},{"time":7.1,"x":1.27,"y":0.02},{"time":8,"x":0,"y":0},{"time":9.1,"x":1.27,"y":0.02},{"time":10,"x":0,"y":0},{"time":11.1,"x":1.27,"y":0.02},{"time":12,"x":0,"y":0}],"scale":[{"time":5.3333,"x":1,"y":1,"curve":"stepped"},{"time":6,"x":1,"y":1,"curve":"stepped"},{"time":8,"x":1,"y":1,"curve":"stepped"},{"time":10,"x":1,"y":1,"curve":"stepped"},{"time":12,"x":1,"y":1}]}},"slots":{"NIco_big_0002_youshou":{"attachment":[{"time":0,"name":"NIco_big_0002_youshou"},{"time":5.8,"name":"NIco_big_0002_youshou"}]},"NIco_big_0003_youqianbi":{"attachment":[{"time":0,"name":"NIco_big_0003_youqianbi"},{"time":5.8,"name":"NIco_big_0003_youqianbi"}]},"NIco_big_0004_youdabi":{"attachment":[{"time":0,"name":"NIco_big_0004_youdabi"},{"time":5.8,"name":"NIco_big_0004_youdabi"}]},"NIco_big_0005_zuoqianbi":{"attachment":[{"time":0,"name":"NIco_big_0005_zuoqianbi"},{"time":5.8333,"name":"NIco_big_0005_zuoqianbi"}]},"NIco_big_0006_zuodabi":{"attachment":[{"time":0,"name":"NIco_big_0006_zuodabi"},{"time":5.8,"name":"NIco_big_0006_zuodabi"}]},"NIco_big_0009_binjiao":{"attachment":[{"time":0,"name":"NIco_big_0009_binjiao"},{"time":5.8,"name":"NIco_big_0009_binjiao"}]},"NIco_big_0011_meimao":{"attachment":[{"time":0,"name":"NIco_big_0011_meimao"},{"time":5.8,"name":"NIco_big_0011_meimao"}]},"NIco_big_0019_yanqiu":{"attachment":[{"time":0,"name":"NIco_big_0019_yanqiu"},{"time":5.8333,"name":"NIco_big_0019_yanqiu"}]},"NIco_big_0023_waiyiyou":{"attachment":[{"time":0,"name":"NIco_big_0023_waiyiyou"},{"time":5.8,"name":"NIco_big_0023_waiyiyou"}]},"NIco_big_0024_youtui":{"attachment":[{"time":0,"name":"NIco_big_0024_youtui"},{"time":5.8,"name":"NIco_big_0024_youtui"}]},"NIco_big_0025_kua":{"attachment":[{"time":0,"name":"NIco_big_0025_kua"},{"time":5.8,"name":"NIco_big_0025_kua"}]},"NIco_big_0026_zuotui":{"attachment":[{"time":0,"name":"NIco_big_0026_zuotui"},{"time":5.8,"name":"NIco_big_0026_zuotui"}]},"NIco_big_0028_shentixia":{"attachment":[{"time":0,"name":"NIco_big_0028_shentixia"},{"time":5.8,"name":"NIco_big_0028_shentixia"}]},"NIco_big_0029_waiyizuo":{"attachment":[{"time":0,"name":"NIco_big_0029_waiyizuo"},{"time":5.8,"name":"NIco_big_0029_waiyizuo"}]},"NIco_big_0030_toufa":{"attachment":[{"time":0,"name":"NIco_big_0030_toufa"},{"time":5.9,"name":"NIco_big_0030_toufa"}]},"rikobig_fin":{"attachment":[{"time":0,"name":null},{"time":5.8,"name":null}]},"NIco_big_0008_liuhai01":{"attachment":[{"time":0,"name":"NIco_big_0008_liuhai01"},{"time":5.8,"name":"NIco_big_0008_liuhai01"}]},"NIco_big_0015_kouxing01":{"attachment":[{"time":0,"name":"NIco_big_0015_kouxing01"},{"time":0.7,"name":"NIco_big_0013_kouxing03"},{"time":0.8333,"name":"NIco_big_0012_kouxing04"},{"time":0.9666,"name":"NIco_big_0014_kouxing02"},{"time":1.1333,"name":"NIco_big_0012_kouxing04"},{"time":1.2666,"name":"NIco_big_0015_kouxing01"},{"time":1.4,"name":"NIco_big_0013_kouxing03"},{"time":1.5333,"name":"NIco_big_0013_kouxing03"},{"time":1.6666,"name":"NIco_big_0012_kouxing04"},{"time":1.8,"name":"NIco_big_0014_kouxing02"},{"time":1.9666,"name":"NIco_big_0012_kouxing04"},{"time":2.1,"name":"NIco_big_0015_kouxing01"},{"time":2.2333,"name":"NIco_big_0013_kouxing03"},{"time":2.4,"name":"NIco_big_0015_kouxing01"},{"time":5.8,"name":"NIco_big_0013_kouxing03"},{"time":8.1,"name":"NIco_big_0015_kouxing01"}]},"NIco_big_0001_zuoshou02":{"attachment":[{"time":0,"name":"NIco_big_0001_zuoshou02"},{"time":6,"name":"NIco_big_0001_zuoshou02"},{"time":7,"name":"NIco_big_0001_zuoshou02"},{"time":8,"name":"NIco_big_0001_zuoshou02"},{"time":9,"name":"NIco_big_0001_zuoshou02"},{"time":10,"name":"NIco_big_0001_zuoshou02"},{"time":11,"name":"NIco_big_0001_zuoshou02"}]},"NIco_big_0010_binjiao2":{"attachment":[{"time":0,"name":"NIco_big_0010_binjiao2"},{"time":5.8,"name":"NIco_big_0010_binjiao2"}]},"NIco_big_0011_meimao2":{"attachment":[{"time":0,"name":"NIco_big_0011_meimao"},{"time":5.8,"name":"NIco_big_0011_meimao"}]},"NIco_big_0019_yanqiu2":{"attachment":[{"time":0,"name":"NIco_big_0019_yanqiu"},{"time":5.8333,"name":"NIco_big_0019_yanqiu"}]},"bone5":{"attachment":[{"time":0,"name":"NIco_big_0020_yanbai"},{"time":5.9,"name":"NIco_big_0020_yanbai"}]},"bone52":{"attachment":[{"time":0,"name":"NIco_big_0018_lian"},{"time":5.9,"name":"NIco_big_0018_lian"}]},"bone53":{"attachment":[{"time":0,"name":"NIco_big_0017_yan"},{"time":0.2,"name":"NIco_big_0016_biyan"},{"time":0.5666,"name":"NIco_big_0017_yan"},{"time":2.1333,"name":"NIco_big_0016_biyan"},{"time":2.2333,"name":"NIco_big_0017_yan"},{"time":4.3333,"name":"NIco_big_0016_biyan"},{"time":4.4333,"name":"NIco_big_0017_yan"},{"time":5.8,"name":"NIco_big_0016_biyan"},{"time":5.9,"name":"NIco_big_0017_yan"},{"time":8,"name":"NIco_big_0016_biyan"},{"time":8.1,"name":"NIco_big_0017_yan"}]},"bone54":{"attachment":[{"time":0,"name":"NIco_big_0031_maozihou"},{"time":5.9,"name":"NIco_big_0031_maozihou"}]},"bone55":{"attachment":[{"time":0,"name":"NIco_big_0007_maoziqian"},{"time":5.9,"name":"NIco_big_0007_maoziqian"}]}},"draworder":[{"time":0},{"time":0.5,"offsets":[{"slot":"NIco_big_0004_youdabi","offset":-8},{"slot":"NIco_big_0003_youqianbi","offset":-10},{"slot":"NIco_big_0002_youshou","offset":-10}]},{"time":0.6,"offsets":[{"slot":"NIco_big_0001_zuoshou02","offset":26},{"slot":"NIco_big_0004_youdabi","offset":-9},{"slot":"NIco_big_0003_youqianbi","offset":-11},{"slot":"NIco_big_0002_youshou","offset":-11}]}]}}}